longitude/__init__.py
longitude/core/__init__.py
longitude/core/caches/__init__.py
longitude/core/caches/base.py
longitude/core/caches/ram.py
longitude/core/caches/redis.py
longitude/core/common/__init__.py
longitude/core/common/exceptions.py
longitude/core/common/helpers.py
longitude/core/common/query_response.py
longitude/core/data_sources/README.md
longitude/core/data_sources/__init__.py
longitude/core/data_sources/base.py
longitude/core/data_sources/base_async.py
longitude/core/data_sources/carto.py
longitude/core/data_sources/carto_async.py
longitude/core/data_sources/postgres/__init__.py
longitude/core/data_sources/postgres/common.py
longitude/core/data_sources/postgres/default.py
longitude/core/data_sources/postgres/sqlalchemy.py
longitude/core/tests/__init__.py
longitude/core/tests/test_cache_base.py
longitude/core/tests/test_cache_ram.py
longitude/core/tests/test_cache_redis.py
longitude/core/tests/test_data_source_carto.py
longitude/core/tests/test_data_source_postgres.py
longitude/core/tests/test_data_source_sqlalchemy.py
longitude/core/tests/test_helpers.py
longitude/core/tests/utils.py
longitude/samples/.gitignore
longitude/samples/README.md
longitude/samples/__init__.py
longitude/samples/aiohttp_oauth2_login.py
longitude/samples/carto_async_sample.py
longitude/samples/carto_sample.py
longitude/samples/carto_sample_with_ram_cache.py
longitude/samples/carto_sample_with_redis_cache.py
longitude/samples/config.py
longitude/samples/copy_from_sample.py
longitude/samples/demo_data.csv
longitude/samples/mixed_datasources.py
longitude/samples/postgres_sample.py
longitude/samples/sqlalchemy_sample.py
longitude/tools/__init__.py
longitude/tools/oauth/__init__.py
longitude/tools/oauth/carto_oauth2_client_aiohttp.py
geographica_longitude-0.10.0.dist-info/LICENSE
geographica_longitude-0.10.0.dist-info/WHEEL
geographica_longitude-0.10.0.dist-info/METADATA
geographica_longitude-0.10.0.dist-info/RECORD
