Metadata-Version: 2.1
Name: geographica-longitude
Version: 0.10.0
Summary: A longitudinal lib
Home-page: https://github.com/GeographicaGS/Longitude
License: MIT
Author: Geographica
Author-email: hello@geographica.com
Requires-Python: >=3.7,<4.0
Classifier: License :: OSI Approved :: MIT License
Classifier: Programming Language :: Python :: 3
Classifier: Programming Language :: Python :: 3.7
Classifier: Programming Language :: Python :: 3.8
Requires-Dist: aioauth-client (>=0.16.2,<0.17.0)
Requires-Dist: aiohttp (>=3.5,<4.0)
Requires-Dist: aredis (>=1.1,<2.0)
Requires-Dist: asyncio (>=3.4,<4.0)
Requires-Dist: carto (>=1.6,<2.0)
Requires-Dist: cartoframes (>=0.9.0,<0.10.0)
Requires-Dist: environs (>=5.0,<6.0)
Requires-Dist: geolibs-cartoasync (>=0.0.4,<0.0.5)
Requires-Dist: pandas (>=1.1,<2.0)
Requires-Dist: psycopg2-binary (>=2.8,<3.0)
Requires-Dist: pyjwt (>=1.7,<2.0)
Requires-Dist: redis (>=3.2,<4.0)
Requires-Dist: sqlalchemy (>=1.1.15,<2.0.0)
